gigapixel/__init__.py
gigapixel/exceptions.py
gigapixel/gigapixel.py
gigapixel/logging.py
gigapixel-1.5.0.dist-info/LICENSE
gigapixel-1.5.0.dist-info/METADATA
gigapixel-1.5.0.dist-info/WHEEL
gigapixel-1.5.0.dist-info/top_level.txt
gigapixel-1.5.0.dist-info/RECORD
