Metadata-Version: 2.1
Name: gigapixel
Version: 1.5.0
Summary: Topaz Gigapixel AI automation tool
Home-page: https://github.com/TimNekk/Gigapixel
Author: TimNekk
Author-email: herew26@gmail.com
License: Apache License, Version 2.0, see LICENSE file
Classifier: License :: OSI Approved :: Apache Software License
Classifier: Operating System :: Microsoft :: Windows
Classifier: Intended Audience :: End Users/Desktop
Classifier: Intended Audience :: Developers
Classifier: Programming Language :: Python
Classifier: Programming Language :: Python :: 3
Classifier: Programming Language :: Python :: 3.6
Classifier: Programming Language :: Python :: 3.7
Classifier: Programming Language :: Python :: 3.8
Classifier: Programming Language :: Python :: 3.9
Classifier: Programming Language :: Python :: 3.10
Classifier: Programming Language :: Python :: 3.11
Classifier: Programming Language :: Python :: 3.12
Classifier: Programming Language :: Python :: 3.13
Classifier: Programming Language :: Python :: Implementation :: PyPy
Classifier: Programming Language :: Python :: Implementation :: CPython
License-File: LICENSE
Requires-Dist: pywinauto
Requires-Dist: clipboard
Requires-Dist: loguru
Provides-Extra: dev
Requires-Dist: flake8==4.0.1; extra == "dev"
Requires-Dist: mypy==0.961; extra == "dev"
